speaksynk_flow_processor/AWSSpeakSynkFlowProcesor.py
speaksynk_flow_processor/SpeakSynkFlowProcessor.py
speaksynk_flow_processor/__init__.py
speaksynk_flow_processor/constants/__init__.py
speaksynk_flow_processor/constants/constants.py
speaksynk_flow_processor/interfaces/IFlow.py
speaksynk_flow_processor/interfaces/IProcessor.py
speaksynk_flow_processor/interfaces/__init__.py
speaksynk_flow_processor/main.py
speaksynk_flow_processor/track/__init__.py
speaksynk_flow_processor/track/track.py
speaksynk_flow_processor/utils/__init__.py
speaksynk_flow_processor/utils/logger.py
speaksynk_flow_processor/utils/process_data.py
speaksynk_flow_processor/utils/utils.py
speaksynk_flow_processor-1.2.8.dist-info/METADATA
speaksynk_flow_processor-1.2.8.dist-info/WHEEL
speaksynk_flow_processor-1.2.8.dist-info/entry_points.txt
speaksynk_flow_processor-1.2.8.dist-info/RECORD
