Metadata-Version: 2.1
Name: speaksynk-flow-processor
Version: 1.2.8
Summary: 
Author: Gustavo Sanchez
Author-email: antero105@gmail.com
Requires-Python: >=3.10,<4.0
Classifier: Programming Language :: Python :: 3
Classifier: Programming Language :: Python :: 3.10
Classifier: Programming Language :: Python :: 3.11
Classifier: Programming Language :: Python :: 3.12
Requires-Dist: boto3 (>=1.28.39,<2.0.0)
Requires-Dist: colorlog (>=6.7.0,<7.0.0)
Requires-Dist: pytest (>=7.4.0,<8.0.0)
